Metadata-Version: 1.2
Name: firedb
Version: 0.2
Summary: Google Cloud FireStore Database Utilities - Backup, Restore, Import, List
Home-page: https://github.com/ipal0/firedb
Author: Pal
Author-email: ipal0can@gmail.com
License: GPL
Platform: UNKNOWN
Requires-Python: >=3
